README
setup.cfg
setup.py
vminute/__init__.py
vminute/vminute.py
vminute.egg-info/PKG-INFO
vminute.egg-info/SOURCES.txt
vminute.egg-info/dependency_links.txt
vminute.egg-info/entry_points.txt
vminute.egg-info/top_level.txt