Metadata-Version: 1.1
Name: vminute
Version: 0.2.31
Summary: A tool for quick creation and deployment of Openstack machines used for QA testing.
Home-page: https://github.com/SatelliteQE/5minute
Author: Martin Korbel
Author-email: mkorbel@redhat.com
License: GNU General Public License v2 (GPLv2)
Keywords: openstack testing deployment
Platform: UNKNOWN
Classifier: Development Status :: 3 - Alpha
Classifier: Intended Audience :: Information Technology
Classifier: Topic :: Software Development :: Quality Assurance
Classifier: License :: OSI Approved :: GNU General Public License v2 (GPLv2)
